{"status":"success","lastModified":"2026-06-01T01:14:48.380Z","data":{"patterns":[{"length":31819,"id":"1418","encodedPolyline":"kfdsFzbyyN`@\\NGHmCGm@bAeAtBhF\\tAVtBDtBWxOLhAz@lC_@^{Bh@?M?LkABkB[v@iEZmAfA@BP?Qj@K`Aw@RiMEwBUsB_@uAuBiFYcBEwAH{@~`@tAoAjt@I?H?QdKM`B{@|D_@bEa@xAJXTBNKD_@Ie@JiCv@eFRmBbAck@n@W@g@?[BwAG]a@YVmN_a@wAAgENAO@EcBUsB{DaRQiAIsALyJ^?_@A?gCj@{^ZAYBR{[R?S?XkQT?U?XkMbLgA@VAWhFk@t@SXs@RUb@Qj@Fr@h@XD|GeABZC[vEk@n@WbAy@hA_@xACU~RIAH@QhNF^qAN?]?\\yH|@rAdUk@DEiASU]B?K?C","direction":"ib"},{"length":14893,"id":"1419","encodedPolyline":"y_csFfnuyN@NaAPOP?RN\\fAHzAIsAeUjKkAGWPmMD?E?TeTaAAy@Pg@PeAz@o@XwEj@C[BZaEf@eAX]@}@m@[Ia@BWLm@hAsLxAC[BZoGl@QvHQ?P?[~QM?L?M|J@hAMrQW?TAk@n_@K~AUAT@W~HFhCLnAfAbF?@FT?@Jd@?@FT?@bB`ITzCArFLh@?l@LbBRbAcAdA[BOjAGpA?B","direction":"ob"}],"stops":[{"name":"Mount Hall Loop","id":"501","service":"clever","latitude":40.003742000001,"longitude":-83.036783000002},{"name":"Carmack 5 + Stop 1","id":"94","service":"clever","latitude":40.002781,"longitude":-83.042454000001},{"name":"Carmack 5 + Stop 2","id":"95","service":"clever","latitude":40.002897999999,"longitude":-83.041104},{"name":"Research Center","id":"15","service":"clever","latitude":39.998260999999,"longitude":-83.043327999999},{"name":"Kinnear Road Lot","id":"18","service":"clever","latitude":39.997739,"longitude":-83.037975000001},{"name":"Blankenship Hall","id":"14","service":"clever","latitude":40.003181999999,"longitude":-83.033337000001},{"name":"Midwest Campus (Eastbound)","id":"20","service":"clever","latitude":40.004251,"longitude":-83.026541000001},{"name":"St. John East Bound","id":"21","service":"clever","latitude":40.004047999999,"longitude":-83.020743999998},{"name":"Knowlton Hall","id":"57","service":"clever","latitude":40.003978999999,"longitude":-83.016142000001},{"name":"Fontana Lab","id":"58","service":"clever","latitude":40.003838999999,"longitude":-83.013196999999},{"name":"Stillman Hall","id":"59","service":"clever","latitude":40.001706000001,"longitude":-83.010660000001},{"name":"Ohio Union (Southbound)","id":"44","service":"clever","latitude":39.997810000001,"longitude":-83.009831},{"name":"Siebert Hall","id":"410","service":"clever","latitude":39.995506999999,"longitude":-83.012071999998},{"name":"Mack Hall","id":"41","service":"clever","latitude":39.995923999999,"longitude":-83.014619999999},{"name":"Herrick Transit Hub","id":"405","service":"clever","latitude":39.997568999999,"longitude":-83.018118999999},{"name":"11th & Worthington","id":"606","service":"clever","latitude":39.995426999999,"longitude":-83.012267000001},{"name":"Ohio Union (Northbound)","id":"43","service":"clever","latitude":39.997857999999,"longitude":-83.009564},{"name":"Arps Hall","id":"62","service":"clever","latitude":40.002478000001,"longitude":-83.010531},{"name":"Blackburn House","id":"55","service":"clever","latitude":40.004003999999,"longitude":-83.012460999999},{"name":"Mason Hall","id":"56","service":"clever","latitude":40.004117,"longitude":-83.015499999999},{"name":"St. John Arena (Westbound)","id":"24","service":"clever","latitude":40.004299999999,"longitude":-83.020758000002},{"name":"Midwest Campus (Westbound)","id":"25","service":"clever","latitude":40.004579000001,"longitude":-83.026416999999}]}}